{
    "id": "1",
    "name": "Маршрут по парку",
    "fullDescription": "Этот живописный маршрут проходит через главный городской парк, мимо озера и исторических памятников. Идеально подходит для неспешной велопрогулки в выходной день.",
    "distance": 5.2,
    "difficulty": "Легкий",
    "estimatedTime": "30 минут",
    "points": [
      {"lat": 55.7558, "lon": 37.6173, "name": "Вход в парк"},
      {"lat": 55.7561, "lon": 37.6190, "name": "Озеро"},
      {"lat": 55.7570, "lon": 37.6180, "name": "Исторический памятник"},
      {"lat": 55.7558, "lon": 37.6173, "name": "Выход из парка"}
    ]
  }